{"images": [{"id": 1, "file_name": "TanSpot01.jpg", "width": 800, "height": 536}, {"id": 2, "file_name": "ts1.jpg", "width": 400, "height": 400}, {"id": 3, "file_name": "ts2.jpg", "width": 1200, "height": 2133}, {"id": 4, "file_name": "ts3.jpg", "width": 3550, "height": 1950}, {"id": 5, "file_name": "yellow_rust.jpg", "width": 262, "height": 400}, {"id": 6, "file_name": "yr1.jpg", "width": 1315, "height": 1655}, {"id": 7, "file_name": "yr2.jpg", "width": 750, "height": 1200}, {"id": 8, "file_name": "yr3.jpg", "width": 350, "height": 232}], "type": "instances", "annotations": [{"segmentation": [[316, 1, 316, 532, 391, 532, 391, 1]], "area": 39825, "iscrowd": 0, "ignore": 0, "image_id": 1, "bbox": [316, 1, 75, 531], "category_id": 1, "id": 1}, {"segmentation": [[383, 2, 383, 532, 467, 532, 467, 2]], "area": 44520, "iscrowd": 0, "ignore": 0, "image_id": 1, "bbox": [383, 2, 84, 530], "category_id": 1, "id": 2}, {"segmentation": [[345, 168, 345, 326, 376, 326, 376, 168]], "area": 4898, "iscrowd": 0, "ignore": 0, "image_id": 1, "bbox": [345, 168, 31, 158], "category_id": 2, "id": 3}, {"segmentation": [[421, 234, 421, 304, 456, 304, 456, 234]], "area": 2450, "iscrowd": 0, "ignore": 0, "image_id": 1, "bbox": [421, 234, 35, 70], "category_id": 2, "id": 4}, {"segmentation": [[136, 1, 136, 398, 347, 398, 347, 1]], "area": 83767, "iscrowd": 0, "ignore": 0, "image_id": 2, "bbox": [136, 1, 211, 397], "category_id": 1, "id": 5}, {"segmentation": [[145, 143, 145, 205, 185, 205, 185, 143]], "area": 2480, "iscrowd": 0, "ignore": 0, "image_id": 2, "bbox": [145, 143, 40, 62], "category_id": 2, "id": 6}, {"segmentation": [[255, 200, 255, 294, 293, 294, 293, 200]], "area": 3572, "iscrowd": 0, "ignore": 0, "image_id": 2, "bbox": [255, 200, 38, 94], "category_id": 2, "id": 7}, {"segmentation": [[201, 302, 201, 358, 241, 358, 241, 302]], "area": 2240, "iscrowd": 0, "ignore": 0, "image_id": 2, "bbox": [201, 302, 40, 56], "category_id": 2, "id": 8}, {"segmentation": [[148, 10, 148, 94, 183, 94, 183, 10]], "area": 2940, "iscrowd": 0, "ignore": 0, "image_id": 2, "bbox": [148, 10, 35, 84], "category_id": 2, "id": 9}, {"segmentation": [[310, 332, 310, 381, 338, 381, 338, 332]], "area": 1372, "iscrowd": 0, "ignore": 0, "image_id": 2, "bbox": [310, 332, 28, 49], "category_id": 2, "id": 10}, {"segmentation": [[12, 18, 12, 2089, 762, 2089, 762, 18]], "area": 1553250, "iscrowd": 0, "ignore": 0, "image_id": 3, "bbox": [12, 18, 750, 2071], "category_id": 1, "id": 11}, {"segmentation": [[112, 339, 112, 827, 292, 827, 292, 339]], "area": 87840, "iscrowd": 0, "ignore": 0, "image_id": 3, "bbox": [112, 339, 180, 488], "category_id": 2, "id": 12}, {"segmentation": [[89, 921, 89, 1241, 260, 1241, 260, 921]], "area": 54720, "iscrowd": 0, "ignore": 0, "image_id": 3, "bbox": [89, 921, 171, 320], "category_id": 2, "id": 13}, {"segmentation": [[380, 773, 380, 1916, 687, 1916, 687, 773]], "area": 350901, "iscrowd": 0, "ignore": 0, "image_id": 3, "bbox": [380, 773, 307, 1143], "category_id": 2, "id": 14}, {"segmentation": [[739, 839, 739, 1414, 1007, 1414, 1007, 839]], "area": 154100, "iscrowd": 0, "ignore": 0, "image_id": 3, "bbox": [739, 839, 268, 575], "category_id": 2, "id": 15}, {"segmentation": [[955, 521, 955, 1775, 1160, 1775, 1160, 521]], "area": 257070, "iscrowd": 0, "ignore": 0, "image_id": 3, "bbox": [955, 521, 205, 1254], "category_id": 2, "id": 16}, {"segmentation": [[843, 695, 843, 1798, 3140, 1798, 3140, 695]], "area": 2533591, "iscrowd": 0, "ignore": 0, "image_id": 4, "bbox": [843, 695, 2297, 1103], "category_id": 1, "id": 17}, {"segmentation": [[2000, 925, 2000, 1071, 2460, 1071, 2460, 925]], "area": 67160, "iscrowd": 0, "ignore": 0, "image_id": 4, "bbox": [2000, 925, 460, 146], "category_id": 2, "id": 18}, {"segmentation": [[2486, 835, 2486, 1035, 3083, 1035, 3083, 835]], "area": 119400, "iscrowd": 0, "ignore": 0, "image_id": 4, "bbox": [2486, 835, 597, 200], "category_id": 2, "id": 19}, {"segmentation": [[1733, 895, 1733, 1018, 1953, 1018, 1953, 895]], "area": 27060, "iscrowd": 0, "ignore": 0, "image_id": 4, "bbox": [1733, 895, 220, 123], "category_id": 2, "id": 20}, {"segmentation": [[1976, 785, 1976, 841, 2180, 841, 2180, 785]], "area": 11424, "iscrowd": 0, "ignore": 0, "image_id": 4, "bbox": [1976, 785, 204, 56], "category_id": 2, "id": 21}, {"segmentation": [[70, 3, 70, 395, 193, 395, 193, 3]], "area": 48216, "iscrowd": 0, "ignore": 0, "image_id": 5, "bbox": [70, 3, 123, 392], "category_id": 1, "id": 22}, {"segmentation": [[87, 4, 87, 393, 126, 393, 126, 4]], "area": 15171, "iscrowd": 0, "ignore": 0, "image_id": 5, "bbox": [87, 4, 39, 389], "category_id": 3, "id": 23}, {"segmentation": [[130, 5, 130, 307, 153, 307, 153, 5]], "area": 6946, "iscrowd": 0, "ignore": 0, "image_id": 5, "bbox": [130, 5, 23, 302], "category_id": 3, "id": 24}, {"segmentation": [[160, 7, 160, 391, 188, 391, 188, 7]], "area": 10752, "iscrowd": 0, "ignore": 0, "image_id": 5, "bbox": [160, 7, 28, 384], "category_id": 3, "id": 25}, {"segmentation": [[565, 16, 565, 1627, 1196, 1627, 1196, 16]], "area": 1016541, "iscrowd": 0, "ignore": 0, "image_id": 6, "bbox": [565, 16, 631, 1611], "category_id": 1, "id": 26}, {"segmentation": [[596, 53, 596, 1269, 770, 1269, 770, 53]], "area": 211584, "iscrowd": 0, "ignore": 0, "image_id": 6, "bbox": [596, 53, 174, 1216], "category_id": 3, "id": 27}, {"segmentation": [[728, 32, 728, 1648, 907, 1648, 907, 32]], "area": 289264, "iscrowd": 0, "ignore": 0, "image_id": 6, "bbox": [728, 32, 179, 1616], "category_id": 3, "id": 28}, {"segmentation": [[907, 732, 907, 1622, 1075, 1622, 1075, 732]], "area": 149520, "iscrowd": 0, "ignore": 0, "image_id": 6, "bbox": [907, 732, 168, 890], "category_id": 3, "id": 29}, {"segmentation": [[259, 16, 259, 1197, 518, 1197, 518, 16]], "area": 305879, "iscrowd": 0, "ignore": 0, "image_id": 7, "bbox": [259, 16, 259, 1181], "category_id": 1, "id": 30}, {"segmentation": [[287, 254, 287, 1006, 395, 1006, 395, 254]], "area": 81216, "iscrowd": 0, "ignore": 0, "image_id": 7, "bbox": [287, 254, 108, 752], "category_id": 3, "id": 31}, {"segmentation": [[394, 136, 394, 1189, 481, 1189, 481, 136]], "area": 91611, "iscrowd": 0, "ignore": 0, "image_id": 7, "bbox": [394, 136, 87, 1053], "category_id": 3, "id": 32}, {"segmentation": [[17, 70, 17, 132, 350, 132, 350, 70]], "area": 20646, "iscrowd": 0, "ignore": 0, "image_id": 8, "bbox": [17, 70, 333, 62], "category_id": 3, "id": 33}], "categories": [{"supercategory": "none", "id": 1, "name": "Leaf"}, {"supercategory": "none", "id": 2, "name": "Tan Spot"}, {"supercategory": "none", "id": 3, "name": "Yellow Rust"}]}